setup.py
OpenAddresses_Machine.egg-info/PKG-INFO
OpenAddresses_Machine.egg-info/SOURCES.txt
OpenAddresses_Machine.egg-info/dependency_links.txt
OpenAddresses_Machine.egg-info/entry_points.txt
OpenAddresses_Machine.egg-info/requires.txt
OpenAddresses_Machine.egg-info/top_level.txt
openaddr/VERSION
openaddr/__init__.py
openaddr/cache.py
openaddr/compat.py
openaddr/conform.py
openaddr/expand.py
openaddr/jobs.py
openaddr/process_one.py
openaddr/render.py
openaddr/sample.py
openaddr/summarize.py
openaddr/ci/__init__.py
openaddr/ci/collect.py
openaddr/ci/enqueue.py
openaddr/ci/objects.py
openaddr/ci/poops.py
openaddr/ci/recreate_db.py
openaddr/ci/run_dequeue.py
openaddr/ci/schema.pgsql
openaddr/ci/webhooks.py
openaddr/ci/worker.py
openaddr/ci/templates/head.html
openaddr/ci/templates/index.html
openaddr/ci/templates/info.html
openaddr/ci/templates/job.html
openaddr/ci/templates/jobs.html
openaddr/ci/templates/run-sample.html
openaddr/ci/templates/runs-table.html
openaddr/ci/templates/set.html
openaddr/ci/templates/sets.html
openaddr/geodata/cb_2013_us_county_20m-2163.dbf
openaddr/geodata/cb_2013_us_county_20m-2163.prj
openaddr/geodata/cb_2013_us_county_20m-2163.shp
openaddr/geodata/cb_2013_us_county_20m-2163.shx
openaddr/geodata/cb_2013_us_county_20m-54029.dbf
openaddr/geodata/cb_2013_us_county_20m-54029.prj
openaddr/geodata/cb_2013_us_county_20m-54029.shp
openaddr/geodata/cb_2013_us_county_20m-54029.shx
openaddr/geodata/cb_2013_us_nation_20m-2163.dbf
openaddr/geodata/cb_2013_us_nation_20m-2163.prj
openaddr/geodata/cb_2013_us_nation_20m-2163.shp
openaddr/geodata/cb_2013_us_nation_20m-2163.shx
openaddr/geodata/cb_2013_us_state_20m-2163.dbf
openaddr/geodata/cb_2013_us_state_20m-2163.prj
openaddr/geodata/cb_2013_us_state_20m-2163.shp
openaddr/geodata/cb_2013_us_state_20m-2163.shx
openaddr/geodata/cb_2013_us_state_20m-54029.dbf
openaddr/geodata/cb_2013_us_state_20m-54029.prj
openaddr/geodata/cb_2013_us_state_20m-54029.shp
openaddr/geodata/cb_2013_us_state_20m-54029.shx
openaddr/geodata/ne_10m_admin_1_states_provinces-54029.cpg
openaddr/geodata/ne_10m_admin_1_states_provinces-54029.dbf
openaddr/geodata/ne_10m_admin_1_states_provinces-54029.prj
openaddr/geodata/ne_10m_admin_1_states_provinces-54029.shp
