Metadata-Version: 1.0
Name: OpenAddresses-Machine
Version: 2.0.0
Summary: In-progress scripts for running OpenAddresses on a complete data set and publishing the results.
Home-page: https://github.com/openaddresses/machine
Author: Michal Migurski
Author-email: mike-pypi@teczno.com
License: UNKNOWN
Platform: UNKNOWN
